lustre/__init__.py
lustre/app.py
lustre/auth.py
lustre/config.py
lustre/database.py
lustre/errors.py
lustre/flashes.py
lustre/global_state.py
lustre/minification.py
lustre/precomputation.py
lustre/responses.py
lustre/sessions.py
lustre/templating.py
lustre/ext/alembic.py
lustre/forms/__init__.py
lustre/forms/templates/forms/checkbox.html
lustre/forms/templates/forms/input.html
lustre/forms/templates/forms/select.html
lustre/forms/templates/forms/textarea.html
lustre-0.4.3.dist-info/LICENSE
lustre-0.4.3.dist-info/METADATA
lustre-0.4.3.dist-info/WHEEL
lustre-0.4.3.dist-info/top_level.txt
lustre-0.4.3.dist-info/RECORD
